ny_pack_1/__init__.py
ny_pack_1/__main__.py
ny_pack_1/print_me_func.py
ny_pack_1-0.1.0.dist-info/licenses/LICENSE.txt
ny_pack_1-0.1.0.dist-info/METADATA
ny_pack_1-0.1.0.dist-info/WHEEL
ny_pack_1-0.1.0.dist-info/entry_points.txt
ny_pack_1-0.1.0.dist-info/top_level.txt
ny_pack_1-0.1.0.dist-info/RECORD
