Metadata-Version: 2.4
Name: ny_pack_1
Version: 0.1.0
Summary: My first package!
Author-email: Nikhil Yadav <nikhilyadav.uk@gmail.com>
Maintainer-email: Nikhil Yadav <nikhilyadav.uk@gmail.com>
License: Copyright 2025 Nikhil Yadav
Project-URL: Homepage, https://github.com/nikhilyadav-git/python-package-101
Project-URL: Documentation, https://github.com/nikhilyadav-git/python-package-101/README.md
Keywords: Nikhil
Classifier: Programming Language :: Python :: 3.9
Classifier: Programming Language :: Python :: Implementation :: CPython
Classifier: License :: OSI Approved :: BSD License
Classifier: Intended Audience :: Developers
Classifier: Operating System :: POSIX :: Linux
Classifier: Operating System :: Microsoft :: Windows
Classifier: Operating System :: MacOS
Classifier: Operating System :: MacOS :: MacOS X
Requires-Python: >=3.9
License-File: LICENSE.txt
Dynamic: license-file
